atomkit/__init__.py
atomkit/_constants.py
atomkit/_deprecation.py
atomkit/_units.py
atomkit/_version.py
atomkit/cli.py
atomkit/py.typed
atomkit/region.py
atomkit/spatial_grid.py
atomkit/viz.py
atomkit/io/__init__.py
atomkit/io/lammps.py
atomkit/marimo/__init__.py
atomkit/marimo/widgets.py
atomkit-0.2.0.dist-info/METADATA
atomkit-0.2.0.dist-info/WHEEL
atomkit-0.2.0.dist-info/entry_points.txt
atomkit-0.2.0.dist-info/licenses/LICENSE
atomkit-0.2.0.dist-info/RECORD
