Metadata-Version: 2.4
Name: atomkit
Version: 0.2.0
Summary: Atom-level analysis toolkit for molecular dynamics trajectories
Project-URL: Homepage, https://github.com/arki05/atomkit
Project-URL: Repository, https://github.com/arki05/atomkit
Project-URL: Issues, https://github.com/arki05/atomkit/issues
Author-email: Julius Arkenberg <julius@rkenberg.de>
License: MIT
License-File: LICENSE
Keywords: chemistry,hdf5,lammps,molecular-dynamics,simulation,spatial-indexing
Classifier: Development Status :: 3 - Alpha
Classifier: Intended Audience :: Science/Research
Classifier: License :: OSI Approved :: MIT License
Classifier: Operating System :: OS Independent
Classifier: Programming Language :: Python :: 3
Classifier: Programming Language :: Python :: 3.10
Classifier: Programming Language :: Python :: 3.11
Classifier: Programming Language :: Python :: 3.12
Classifier: Topic :: Scientific/Engineering :: Chemistry
Classifier: Topic :: Scientific/Engineering :: Physics
Classifier: Typing :: Typed
Requires-Python: >=3.10
Requires-Dist: h5py>=3.0
Requires-Dist: numba>=0.56
Requires-Dist: numpy>=1.24
Requires-Dist: pint>=0.23
Requires-Dist: polars>=0.19
Requires-Dist: tqdm>=4.60
Provides-Extra: all
Requires-Dist: hdf5plugin>=4.0; extra == 'all'
Requires-Dist: marimo>=0.1; extra == 'all'
Requires-Dist: matplotlib>=3.5; extra == 'all'
Provides-Extra: compression
Requires-Dist: hdf5plugin>=4.0; extra == 'compression'
Provides-Extra: dev
Requires-Dist: hdf5plugin>=4.0; extra == 'dev'
Requires-Dist: matplotlib>=3.5; extra == 'dev'
Requires-Dist: pytest-cov>=4.0; extra == 'dev'
Requires-Dist: pytest-xdist>=3.0; extra == 'dev'
Requires-Dist: pytest>=7.0; extra == 'dev'
Provides-Extra: marimo
Requires-Dist: marimo>=0.1; extra == 'marimo'
Requires-Dist: matplotlib>=3.5; extra == 'marimo'
Provides-Extra: viz
Requires-Dist: matplotlib>=3.5; extra == 'viz'
